pyteomics/_capi.py
pyteomics/ccompat.pxd
pyteomics/cmass.c
pyteomics/cmass.cp38-win_amd64.pyd
pyteomics/cmass.pxd
pyteomics/cmass.pyx
pyteomics/compat.h
pyteomics/cparser.c
pyteomics/cparser.cp38-win_amd64.pyd
pyteomics/cparser.pxd
pyteomics/cparser.pyx
pyteomics_cythonize-0.2.9.dist-info/LICENSE
pyteomics_cythonize-0.2.9.dist-info/METADATA
pyteomics_cythonize-0.2.9.dist-info/WHEEL
pyteomics_cythonize-0.2.9.dist-info/top_level.txt
pyteomics_cythonize-0.2.9.dist-info/RECORD
