Metadata-Version: 2.1
Name: pyteomics.cythonize
Version: 0.2.9
Summary: An Cython-accelerated version of common pyteomics functions
Home-page: https://github.com/mobiusklein/pyteomics.cythonize
Maintainer: Joshua Klein
Maintainer-email: jaklein@bu.edu
License: License :: OSI Approved :: Apache Software License
Classifier: Intended Audience :: Science/Research
Classifier: Programming Language :: Python :: 3
Classifier: Topic :: Education
Classifier: Topic :: Scientific/Engineering :: Bio-Informatics
Classifier: Topic :: Scientific/Engineering :: Chemistry
Classifier: Topic :: Software Development :: Libraries
License-File: LICENSE
Requires-Dist: pyteomics
